allocation_o2/__init__.py
allocation_o2/__main__.py
allocation_o2/allocation_o2.cpython-312-x86_64-linux-gnu.so
allocation_o2/allocation_o2.so
allocation_o2/allocator_factory.py
allocation_o2/capital_allocator.py
allocation_o2-1.1.0.dist-info/licenses/LICENSE
allocation_o2-1.1.0.dist-info/METADATA
allocation_o2-1.1.0.dist-info/WHEEL
allocation_o2-1.1.0.dist-info/top_level.txt
allocation_o2-1.1.0.dist-info/RECORD
