Metadata-Version: 2.4
Name: allocation_o2
Version: 1.1.0
Summary: Tactical asset allocation library with Rust backend
Author-email: Vlad Kochetov <vladkoch@knu.ua>
Project-URL: Homepage, https://github.com/VladKochetov007/allocation_o2
Project-URL: Bug Tracker, https://github.com/VladKochetov007/allocation_o2/issues
Classifier: Development Status :: 3 - Alpha
Classifier: Intended Audience :: Developers
Classifier: Intended Audience :: Financial and Insurance Industry
Classifier: Programming Language :: Python :: 3
Classifier: Programming Language :: Python :: 3.8
Classifier: Programming Language :: Python :: 3.9
Classifier: Programming Language :: Python :: 3.10
Classifier: Programming Language :: Python :: 3.11
Classifier: Programming Language :: Rust
Classifier: Topic :: Scientific/Engineering :: Mathematics
Classifier: Topic :: Office/Business :: Financial :: Investment
Requires-Python: >=3.8
License-File: LICENSE
Requires-Dist: numpy>=1.20.0
Requires-Dist: matplotlib>=3.5.0
Dynamic: license-file
